lkspacecraft/__init__.py
lkspacecraft/data/kernels/testkernels/earth_sun_moon_kepler.bsp
lkspacecraft/data/kernels/testkernels/earth_sun_moon_tess.bsp
lkspacecraft/data/kernels/testkernels/kplr2012299191755.tsc
lkspacecraft/data/kernels/testkernels/kplr2013205175543.tsc
lkspacecraft/data/kernels/testkernels/kplr2018134232543.tsc
lkspacecraft/data/kernels/testkernels/naif0012.tls
lkspacecraft/data/kernels/testkernels/tess2018236164754-41096_sclk.tsc
lkspacecraft/spacecraft.py
lkspacecraft/utils.py
lkspacecraft-1.3.1.dist-info/METADATA
lkspacecraft-1.3.1.dist-info/WHEEL
lkspacecraft-1.3.1.dist-info/licenses/LICENSE
lkspacecraft-1.3.1.dist-info/RECORD
